varun_portal_gun/__init__.py
varun_portal_gun/bdc_autobias.py
varun_portal_gun/bdc_gain.py
varun_portal_gun/bdc_power_det.py
varun_portal_gun/fb_power_det.py
varun_portal_gun/main.py
varun_portal_gun-0.147.0.dist-info/METADATA
varun_portal_gun-0.147.0.dist-info/WHEEL
varun_portal_gun-0.147.0.dist-info/entry_points.txt
varun_portal_gun-0.147.0.dist-info/RECORD
