Metadata-Version: 2.3
Name: varun-portal-gun
Version: 0.147.0
Summary: 
Author: Varun Yelluru
Author-email: vyelluru@gmail.com
Requires-Python: >=3.12
Classifier: Programming Language :: Python :: 3
Classifier: Programming Language :: Python :: 3.12
Classifier: Programming Language :: Python :: 3.13
Requires-Dist: typer (>=0.16.0,<0.17.0)
